fin_hedge/__init__.py
fin_hedge/computational_pricing.py
fin_hedge/financial_pricing.py
fin_hedge/portfolio_optimization.py
fin_hedge/statistical_test.py
fin_hedge-0.0.2.dist-info/METADATA
fin_hedge-0.0.2.dist-info/RECORD
fin_hedge-0.0.2.dist-info/WHEEL
fin_hedge-0.0.2.dist-info/top_level.txt
