Metadata-Version: 2.1
Name: fin-hedge
Version: 0.0.2
Summary: A package for quant finance
Home-page: https://github.com/biadeneedo/fin_hedge
Author: edob
Author-email: biadene.edoardo@gmail.com
Classifier: Programming Language :: Python :: 3
Classifier: License :: OSI Approved :: MIT License
Classifier: Operating System :: OS Independent
Requires-Python: >=3.6
License-File: LICENSE.txt
